LICENSE
MANIFEST.in
README.rst
setup.py
configmanager/__init__.py
configmanager/base.py
configmanager/changesets.py
configmanager/click_ext.py
configmanager/exceptions.py
configmanager/item_types.py
configmanager/items.py
configmanager/managers.py
configmanager/meta.py
configmanager/persistence.py
configmanager/plain.py
configmanager/schema_parser.py
configmanager/sections.py
configmanager/utils.py
configmanager.egg-info/PKG-INFO
configmanager.egg-info/SOURCES.txt
configmanager.egg-info/dependency_links.txt
configmanager.egg-info/requires.txt
configmanager.egg-info/top_level.txt
docs/.gitignore
docs/Makefile
docs/conf.py
docs/index.rst
docs/v1/api.rst.inc
docs/v1/click.rst.inc
docs/v1/design.rst.inc
docs/v1/exceptions.rst.inc
docs/v1/guide.rst.inc
docs/v1/hooks.rst.inc
docs/v1/index.rst
docs/v1/introduction.rst.inc
docs/v1/iterators.rst.inc
docs/v1/names.rst.inc
docs/v1/quickstart.rst.inc
docs/v1/schemas.rst.inc
tests/__init__.py
tests/conftest.py
tests/test_changesets.py
tests/test_click.py
tests/test_config.py
tests/test_configparser.py
tests/test_envvar.py
tests/test_exceptions.py
tests/test_extending_library.py
tests/test_hooks.py
tests/test_item.py
tests/test_item_awareness.py
tests/test_item_get_set.py
tests/test_iterators.py
tests/test_json.py
tests/test_load.py
tests/test_plain_config.py
tests/test_proxies.py
tests/test_schema_parser.py
tests/test_section.py
tests/test_types.py
tests/test_user_app_config.py
tests/test_v1.py
tests/test_validation.py
tests/test_yaml.py