Metadata-Version: 2.1
Name: configmanager
Version: 1.34.1
Summary: Forget about configparser, YAML, or JSON parsers. Focus on configuration.
Home-page: https://github.com/jbasko/configmanager
Author: Jazeps Basko
Author-email: jazeps.basko@gmail.com
Maintainer: Jazeps Basko
Maintainer-email: jazeps.basko@gmail.com
License: MIT
Platform: UNKNOWN
Classifier: Development Status :: 4 - Beta
Classifier: Intended Audience :: Developers
Classifier: Programming Language :: Python
Classifier: Programming Language :: Python :: 2
Classifier: Programming Language :: Python :: 2.7
Classifier: Programming Language :: Python :: 3
Classifier: Programming Language :: Python :: 3.5
Classifier: Programming Language :: Python :: 3.6
Classifier: Programming Language :: Python :: 3.7
Classifier: License :: OSI Approved :: MIT License
Provides-Extra: click
Provides-Extra: yaml
